MANIFEST.in
README.md
setup.cfg
setup.py
healthcareai/__init__.py
healthcareai/advanced_supvervised_model_trainer.py
healthcareai/supervised_model_trainer.py
healthcareai.egg-info/PKG-INFO
healthcareai.egg-info/SOURCES.txt
healthcareai.egg-info/dependency_links.txt
healthcareai.egg-info/not-zip-safe
healthcareai.egg-info/requires.txt
healthcareai.egg-info/top_level.txt
healthcareai/common/__init__.py
healthcareai/common/azure_blob_storage_helper.py
healthcareai/common/catalyst_sqlite_db_fixtures.py
healthcareai/common/csv_loader.py
healthcareai/common/database_connections.py
healthcareai/common/database_library_validators.py
healthcareai/common/database_validators.py
healthcareai/common/database_writers.py
healthcareai/common/feature_availability_profiler.py
healthcareai/common/file_io_utilities.py
healthcareai/common/filters.py
healthcareai/common/get_categorical_levels.py
healthcareai/common/healthcareai_error.py
healthcareai/common/helpers.py
healthcareai/common/impact_coding.py
healthcareai/common/model_eval.py
healthcareai/common/predict.py
healthcareai/common/randomized_search.py
healthcareai/common/table_archiver.py
healthcareai/common/top_factors.py
healthcareai/common/transformers.py
healthcareai/datasets/__init__.py
healthcareai/datasets/base.py
healthcareai/datasets/data/diabetes.csv
healthcareai/pipelines/__init__.py
healthcareai/pipelines/data_preparation.py
healthcareai/tests/__init__.py
healthcareai/tests/helpers.py
healthcareai/tests/test_advanced_trainer.py
healthcareai/tests/test_categorical_levels.py
healthcareai/tests/test_csv_loader.py
healthcareai/tests/test_database_validation.py
healthcareai/tests/test_dataframe_filters.py
healthcareai/tests/test_dataframe_transformers.py
healthcareai/tests/test_feature_availability_profiler.py
healthcareai/tests/test_file_utilities.py
healthcareai/tests/test_impact_coding.py
healthcareai/tests/test_model_eval.py
healthcareai/tests/test_model_eval_helpers.py
healthcareai/tests/test_predict.py
healthcareai/tests/test_top_factors.py
healthcareai/tests/test_trained_supervised_model.py
healthcareai/tests/test_trainer.py
healthcareai/trained_models/__init__.py
healthcareai/trained_models/trained_supervised_model.py